vimbuilder/__init__.py
vimbuilder/builder.py
vimbuilder-0.0.4.dist-info/METADATA
vimbuilder-0.0.4.dist-info/WHEEL
vimbuilder-0.0.4.dist-info/licenses/LICENSE
vimbuilder-0.0.4.dist-info/RECORD
