Metadata-Version: 2.1
Name: vimbuilder
Version: 0.0.4
Summary: Sphinx extension to generate Vim help files
Project-URL: Homepage, https://github.com/girishji/vimbuilder
Project-URL: Bug Tracker, https://github.com/girishji/vimbuilder/issues
Author-email: Girish Palya <girishji@gmail.com>
License-File: LICENSE
Keywords: builder,docs,documentation,sphinx,sphinx-extention,vim,vim-help
Classifier: License :: OSI Approved :: MIT License
Classifier: Operating System :: OS Independent
Classifier: Programming Language :: Python :: 3
Requires-Python: >=3.7
